com_digitalruiz_shopify_http_client/__init__.py
com_digitalruiz_shopify_http_client/shopify_http_client.py
com_digitalruiz_shopify_http_client-0.0.10.dist-info/LICENSE
com_digitalruiz_shopify_http_client-0.0.10.dist-info/METADATA
com_digitalruiz_shopify_http_client-0.0.10.dist-info/WHEEL
com_digitalruiz_shopify_http_client-0.0.10.dist-info/top_level.txt
com_digitalruiz_shopify_http_client-0.0.10.dist-info/RECORD
